{
    "Markers": [
        {
            "endDatetime": "2020-12-28T14:37:07.257876+03:00",
            "extras": {
            },
            "index": 1,
            "label": "Onset",
            "originalEndDatetime": "2020-12-28T14:37:07.260590+03:00",
            "originalStartDatetime": "2020-12-28T14:37:07.260590+03:00",
            "port": "KeyStroke",
            "startDatetime": "2020-12-28T14:37:07.257876+03:00",
            "type": "instance",
            "uuid": "e5e74e87-4835-49b3-bdbd-381d515e9712",
            "value": 1
        },
        {
            "endDatetime": "2020-12-28T14:37:15.279030+03:00",
            "extras": {
            },
            "index": 2,
            "label": "Onset",
            "originalEndDatetime": "2020-12-28T14:37:15.275259+03:00",
            "originalStartDatetime": "2020-12-28T14:37:15.275259+03:00",
            "port": "KeyStroke",
            "startDatetime": "2020-12-28T14:37:15.279030+03:00",
            "type": "instance",
            "uuid": "71c1bc89-9b65-46aa-ae1e-d9375dbd0d7c",
            "value": 1
        },
        {
            "endDatetime": "2020-12-28T14:37:23.267854+03:00",
            "extras": {
            },
            "index": 3,
            "label": "Onset",
            "originalEndDatetime": "2020-12-28T14:37:23.270044+03:00",
            "originalStartDatetime": "2020-12-28T14:37:23.270044+03:00",
            "port": "KeyStroke",
            "startDatetime": "2020-12-28T14:37:23.267854+03:00",
            "type": "instance",
            "uuid": "5500fca9-e08e-4d71-90d2-89a3bea6ba04",
            "value": 1
        },
        {
            "endDatetime": "2020-12-28T14:37:31.291455+03:00",
            "extras": {
            },
            "index": 4,
            "label": "Onset",
            "originalEndDatetime": "2020-12-28T14:37:31.292139+03:00",
            "originalStartDatetime": "2020-12-28T14:37:31.292139+03:00",
            "port": "KeyStroke",
            "startDatetime": "2020-12-28T14:37:31.291455+03:00",
            "type": "instance",
            "uuid": "5b1bf55c-0d8b-4120-a0ce-e8a34d1bd62e",
            "value": 1
        },
        {
            "endDatetime": "2020-12-28T14:37:39.282973+03:00",
            "extras": {
            },
            "index": 5,
            "label": "Onset",
            "originalEndDatetime": "2020-12-28T14:37:39.286631+03:00",
            "originalStartDatetime": "2020-12-28T14:37:39.286631+03:00",
            "port": "KeyStroke",
            "startDatetime": "2020-12-28T14:37:39.282973+03:00",
            "type": "instance",
            "uuid": "ddcfb47f-4674-404d-988c-4ff0d5bd72b0",
            "value": 1
        },
        {
            "endDatetime": "2020-12-28T14:37:47.261554+03:00",
            "extras": {
            },
            "index": 6,
            "label": "Onset",
            "originalEndDatetime": "2020-12-28T14:37:47.265151+03:00",
            "originalStartDatetime": "2020-12-28T14:37:47.265151+03:00",
            "port": "KeyStroke",
            "startDatetime": "2020-12-28T14:37:47.261554+03:00",
            "type": "instance",
            "uuid": "2e67df34-d5ad-421d-8f56-f910f0e19093",
            "value": 1
        },
        {
            "endDatetime": "2020-12-28T14:37:55.255393+03:00",
            "extras": {
            },
            "index": 7,
            "label": "Onset",
            "originalEndDatetime": "2020-12-28T14:37:55.257901+03:00",
            "originalStartDatetime": "2020-12-28T14:37:55.257901+03:00",
            "port": "KeyStroke",
            "startDatetime": "2020-12-28T14:37:55.255393+03:00",
            "type": "instance",
            "uuid": "d8bf1021-ef07-48ba-9824-a910ac842b21",
            "value": 1
        },
        {
            "endDatetime": "2020-12-28T14:38:03.261407+03:00",
            "extras": {
            },
            "index": 8,
            "label": "Onset",
            "originalEndDatetime": "2020-12-28T14:38:03.259279+03:00",
            "originalStartDatetime": "2020-12-28T14:38:03.259279+03:00",
            "port": "KeyStroke",
            "startDatetime": "2020-12-28T14:38:03.261407+03:00",
            "type": "instance",
            "uuid": "6c340630-3194-40bd-88b7-00283c238925",
            "value": 1
        },
        {
            "endDatetime": "2020-12-28T14:38:11.266040+03:00",
            "extras": {
            },
            "index": 9,
            "label": "Onset",
            "originalEndDatetime": "2020-12-28T14:38:11.263663+03:00",
            "originalStartDatetime": "2020-12-28T14:38:11.263663+03:00",
            "port": "KeyStroke",
            "startDatetime": "2020-12-28T14:38:11.266040+03:00",
            "type": "instance",
            "uuid": "087c9708-a18d-49f4-b62c-13e225431abb",
            "value": 1
        },
        {
            "endDatetime": "2020-12-28T14:38:19.264355+03:00",
            "extras": {
            },
            "index": 10,
            "label": "Onset",
            "originalEndDatetime": "2020-12-28T14:38:19.261581+03:00",
            "originalStartDatetime": "2020-12-28T14:38:19.261581+03:00",
            "port": "KeyStroke",
            "startDatetime": "2020-12-28T14:38:19.264355+03:00",
            "type": "instance",
            "uuid": "0a43d5c1-4942-45ce-993c-5ed819a21347",
            "value": 1
        },
        {
            "endDatetime": "2020-12-28T14:38:27.249519+03:00",
            "extras": {
            },
            "index": 11,
            "label": "Onset",
            "originalEndDatetime": "2020-12-28T14:38:27.246491+03:00",
            "originalStartDatetime": "2020-12-28T14:38:27.246491+03:00",
            "port": "KeyStroke",
            "startDatetime": "2020-12-28T14:38:27.249519+03:00",
            "type": "instance",
            "uuid": "82a01d74-3c85-4d49-91ba-67933a479e20",
            "value": 1
        },
        {
            "endDatetime": "2020-12-28T14:38:35.258326+03:00",
            "extras": {
            },
            "index": 12,
            "label": "Onset",
            "originalEndDatetime": "2020-12-28T14:38:35.255824+03:00",
            "originalStartDatetime": "2020-12-28T14:38:35.255824+03:00",
            "port": "KeyStroke",
            "startDatetime": "2020-12-28T14:38:35.258326+03:00",
            "type": "instance",
            "uuid": "aa7613f3-06f6-4ee5-8544-68d557b11a2f",
            "value": 1
        },
        {
            "endDatetime": "2020-12-28T14:38:43.259063+03:00",
            "extras": {
            },
            "index": 13,
            "label": "Onset",
            "originalEndDatetime": "2020-12-28T14:38:43.257471+03:00",
            "originalStartDatetime": "2020-12-28T14:38:43.257471+03:00",
            "port": "KeyStroke",
            "startDatetime": "2020-12-28T14:38:43.259063+03:00",
            "type": "instance",
            "uuid": "53876d0b-1790-4df5-a7d1-a1b7d34bec4d",
            "value": 1
        },
        {
            "endDatetime": "2020-12-28T14:38:51.243874+03:00",
            "extras": {
            },
            "index": 14,
            "label": "Onset",
            "originalEndDatetime": "2020-12-28T14:38:51.244704+03:00",
            "originalStartDatetime": "2020-12-28T14:38:51.244704+03:00",
            "port": "KeyStroke",
            "startDatetime": "2020-12-28T14:38:51.243874+03:00",
            "type": "instance",
            "uuid": "a906019e-48f4-4453-9e01-f48bf0a7ecb2",
            "value": 1
        },
        {
            "endDatetime": "2020-12-28T14:38:59.275488+03:00",
            "extras": {
            },
            "index": 15,
            "label": "Onset",
            "originalEndDatetime": "2020-12-28T14:38:59.275424+03:00",
            "originalStartDatetime": "2020-12-28T14:38:59.275424+03:00",
            "port": "KeyStroke",
            "startDatetime": "2020-12-28T14:38:59.275488+03:00",
            "type": "instance",
            "uuid": "1245f3d0-daef-4b09-b000-452b751d9b3a",
            "value": 1
        },
        {
            "endDatetime": "2020-12-28T14:39:07.253844+03:00",
            "extras": {
            },
            "index": 16,
            "label": "Onset",
            "originalEndDatetime": "2020-12-28T14:39:07.257502+03:00",
            "originalStartDatetime": "2020-12-28T14:39:07.257502+03:00",
            "port": "KeyStroke",
            "startDatetime": "2020-12-28T14:39:07.253844+03:00",
            "type": "instance",
            "uuid": "dd1deae8-d703-460a-af9b-82642d3276ae",
            "value": 1
        },
        {
            "endDatetime": "2020-12-28T14:39:15.238578+03:00",
            "extras": {
            },
            "index": 17,
            "label": "Onset",
            "originalEndDatetime": "2020-12-28T14:39:15.238544+03:00",
            "originalStartDatetime": "2020-12-28T14:39:15.238544+03:00",
            "port": "KeyStroke",
            "startDatetime": "2020-12-28T14:39:15.238578+03:00",
            "type": "instance",
            "uuid": "ecbce43f-f334-44a2-9fc4-a1dffff454d3",
            "value": 1
        },
        {
            "endDatetime": "2020-12-28T14:39:23.230841+03:00",
            "extras": {
            },
            "index": 18,
            "label": "Onset",
            "originalEndDatetime": "2020-12-28T14:39:23.230770+03:00",
            "originalStartDatetime": "2020-12-28T14:39:23.230770+03:00",
            "port": "KeyStroke",
            "startDatetime": "2020-12-28T14:39:23.230841+03:00",
            "type": "instance",
            "uuid": "32c0b762-3f54-4508-a19e-7dd191bc3add",
            "value": 1
        },
        {
            "endDatetime": "2020-12-28T14:39:31.239852+03:00",
            "extras": {
            },
            "index": 19,
            "label": "Onset",
            "originalEndDatetime": "2020-12-28T14:39:31.238071+03:00",
            "originalStartDatetime": "2020-12-28T14:39:31.238071+03:00",
            "port": "KeyStroke",
            "startDatetime": "2020-12-28T14:39:31.239852+03:00",
            "type": "instance",
            "uuid": "4d21fc28-6730-41ef-b12c-76625ca2762c",
            "value": 1
        },
        {
            "endDatetime": "2020-12-28T14:39:39.232606+03:00",
            "extras": {
            },
            "index": 20,
            "label": "Onset",
            "originalEndDatetime": "2020-12-28T14:39:39.229109+03:00",
            "originalStartDatetime": "2020-12-28T14:39:39.229109+03:00",
            "port": "KeyStroke",
            "startDatetime": "2020-12-28T14:39:39.232606+03:00",
            "type": "instance",
            "uuid": "4ec2a3b1-f4b0-48a7-9645-5661ff85bb4b",
            "value": 1
        },
        {
            "endDatetime": "2020-12-28T14:39:47.225121+03:00",
            "extras": {
            },
            "index": 21,
            "label": "Onset",
            "originalEndDatetime": "2020-12-28T14:39:47.227869+03:00",
            "originalStartDatetime": "2020-12-28T14:39:47.227869+03:00",
            "port": "KeyStroke",
            "startDatetime": "2020-12-28T14:39:47.225121+03:00",
            "type": "instance",
            "uuid": "1112be5e-e4e3-4d36-a459-eee733a73418",
            "value": 1
        },
        {
            "endDatetime": "2020-12-28T14:39:55.248943+03:00",
            "extras": {
            },
            "index": 22,
            "label": "Onset",
            "originalEndDatetime": "2020-12-28T14:39:55.250603+03:00",
            "originalStartDatetime": "2020-12-28T14:39:55.250603+03:00",
            "port": "KeyStroke",
            "startDatetime": "2020-12-28T14:39:55.248943+03:00",
            "type": "instance",
            "uuid": "ed0f5d2f-e924-45a9-81b2-4273c7df164b",
            "value": 1
        },
        {
            "endDatetime": "2020-12-28T14:40:03.242269+03:00",
            "extras": {
            },
            "index": 23,
            "label": "Onset",
            "originalEndDatetime": "2020-12-28T14:40:03.242443+03:00",
            "originalStartDatetime": "2020-12-28T14:40:03.242443+03:00",
            "port": "KeyStroke",
            "startDatetime": "2020-12-28T14:40:03.242269+03:00",
            "type": "instance",
            "uuid": "782c12f8-6939-4e50-b6f0-1f20a5d9c184",
            "value": 1
        },
        {
            "endDatetime": "2020-12-28T14:40:11.227537+03:00",
            "extras": {
            },
            "index": 24,
            "label": "Onset",
            "originalEndDatetime": "2020-12-28T14:40:11.227317+03:00",
            "originalStartDatetime": "2020-12-28T14:40:11.227317+03:00",
            "port": "KeyStroke",
            "startDatetime": "2020-12-28T14:40:11.227537+03:00",
            "type": "instance",
            "uuid": "71b5e02f-9f05-4a7f-9eab-46aaa270a19c",
            "value": 1
        },
        {
            "endDatetime": "2020-12-28T14:40:19.227598+03:00",
            "extras": {
            },
            "index": 25,
            "label": "Onset",
            "originalEndDatetime": "2020-12-28T14:40:19.227111+03:00",
            "originalStartDatetime": "2020-12-28T14:40:19.227111+03:00",
            "port": "KeyStroke",
            "startDatetime": "2020-12-28T14:40:19.227598+03:00",
            "type": "instance",
            "uuid": "2c1fbf01-bcff-4088-b22f-e84e52e56afb",
            "value": 1
        },
        {
            "endDatetime": "2020-12-28T14:40:27.228954+03:00",
            "extras": {
            },
            "index": 26,
            "label": "Onset",
            "originalEndDatetime": "2020-12-28T14:40:27.231295+03:00",
            "originalStartDatetime": "2020-12-28T14:40:27.231295+03:00",
            "port": "KeyStroke",
            "startDatetime": "2020-12-28T14:40:27.228954+03:00",
            "type": "instance",
            "uuid": "dc8c51fd-1035-482c-862b-c48f954f39a3",
            "value": 1
        },
        {
            "endDatetime": "2020-12-28T14:40:35.245141+03:00",
            "extras": {
            },
            "index": 27,
            "label": "Onset",
            "originalEndDatetime": "2020-12-28T14:40:35.245169+03:00",
            "originalStartDatetime": "2020-12-28T14:40:35.245169+03:00",
            "port": "KeyStroke",
            "startDatetime": "2020-12-28T14:40:35.245141+03:00",
            "type": "instance",
            "uuid": "0a791835-7c35-42f9-9d71-5acfd5fb5f07",
            "value": 1
        },
        {
            "endDatetime": "2020-12-28T14:40:43.238097+03:00",
            "extras": {
            },
            "index": 28,
            "label": "Onset",
            "originalEndDatetime": "2020-12-28T14:40:43.237134+03:00",
            "originalStartDatetime": "2020-12-28T14:40:43.237134+03:00",
            "port": "KeyStroke",
            "startDatetime": "2020-12-28T14:40:43.238097+03:00",
            "type": "instance",
            "uuid": "5be83b3f-9037-4938-9b43-2ecd16a4c936",
            "value": 1
        },
        {
            "endDatetime": "2020-12-28T14:40:51.244299+03:00",
            "extras": {
            },
            "index": 29,
            "label": "Onset",
            "originalEndDatetime": "2020-12-28T14:40:51.244775+03:00",
            "originalStartDatetime": "2020-12-28T14:40:51.244775+03:00",
            "port": "KeyStroke",
            "startDatetime": "2020-12-28T14:40:51.244299+03:00",
            "type": "instance",
            "uuid": "ab9387ca-d7de-4666-a1ec-9a292091f6b4",
            "value": 1
        },
        {
            "endDatetime": "2020-12-28T14:40:59.239495+03:00",
            "extras": {
            },
            "index": 30,
            "label": "Onset",
            "originalEndDatetime": "2020-12-28T14:40:59.237455+03:00",
            "originalStartDatetime": "2020-12-28T14:40:59.237455+03:00",
            "port": "KeyStroke",
            "startDatetime": "2020-12-28T14:40:59.239495+03:00",
            "type": "instance",
            "uuid": "ddf5bea2-7cb1-4246-984c-31fc2beacec8",
            "value": 1
        },
        {
            "endDatetime": "2020-12-28T14:41:07.216715+03:00",
            "extras": {
            },
            "index": 31,
            "label": "Onset",
            "originalEndDatetime": "2020-12-28T14:41:07.219631+03:00",
            "originalStartDatetime": "2020-12-28T14:41:07.219631+03:00",
            "port": "KeyStroke",
            "startDatetime": "2020-12-28T14:41:07.216715+03:00",
            "type": "instance",
            "uuid": "3d39fecb-5ed8-48ba-85dc-7c169e6e6ac8",
            "value": 1
        },
        {
            "endDatetime": "2020-12-28T14:41:15.248396+03:00",
            "extras": {
            },
            "index": 32,
            "label": "Onset",
            "originalEndDatetime": "2020-12-28T14:41:15.246356+03:00",
            "originalStartDatetime": "2020-12-28T14:41:15.246356+03:00",
            "port": "KeyStroke",
            "startDatetime": "2020-12-28T14:41:15.248396+03:00",
            "type": "instance",
            "uuid": "da0ff420-a2bb-4dfe-bb8e-a6b7e02f93b7",
            "value": 1
        },
        {
            "endDatetime": "2020-12-28T14:41:23.217525+03:00",
            "extras": {
            },
            "index": 33,
            "label": "Onset",
            "originalEndDatetime": "2020-12-28T14:41:23.219827+03:00",
            "originalStartDatetime": "2020-12-28T14:41:23.219827+03:00",
            "port": "KeyStroke",
            "startDatetime": "2020-12-28T14:41:23.217525+03:00",
            "type": "instance",
            "uuid": "f33ca4b1-65e5-4baf-9839-f278ce586761",
            "value": 1
        },
        {
            "endDatetime": "2020-12-28T14:41:31.233899+03:00",
            "extras": {
            },
            "index": 34,
            "label": "Onset",
            "originalEndDatetime": "2020-12-28T14:41:31.232989+03:00",
            "originalStartDatetime": "2020-12-28T14:41:31.232989+03:00",
            "port": "KeyStroke",
            "startDatetime": "2020-12-28T14:41:31.233899+03:00",
            "type": "instance",
            "uuid": "d3dae539-ba65-46da-ba40-3b6a8365cd72",
            "value": 1
        },
        {
            "endDatetime": "2020-12-28T14:41:39.250256+03:00",
            "extras": {
            },
            "index": 35,
            "label": "Onset",
            "originalEndDatetime": "2020-12-28T14:41:39.246545+03:00",
            "originalStartDatetime": "2020-12-28T14:41:39.246545+03:00",
            "port": "KeyStroke",
            "startDatetime": "2020-12-28T14:41:39.250256+03:00",
            "type": "instance",
            "uuid": "c90490c9-92b4-45db-9595-a05ae87d17aa",
            "value": 1
        },
        {
            "endDatetime": "2020-12-28T14:41:47.212369+03:00",
            "extras": {
            },
            "index": 36,
            "label": "Onset",
            "originalEndDatetime": "2020-12-28T14:41:47.209910+03:00",
            "originalStartDatetime": "2020-12-28T14:41:47.209910+03:00",
            "port": "KeyStroke",
            "startDatetime": "2020-12-28T14:41:47.212369+03:00",
            "type": "instance",
            "uuid": "e163add0-0ea2-4e59-98ce-2614fbed2746",
            "value": 1
        },
        {
            "endDatetime": "2020-12-28T14:41:55.204673+03:00",
            "extras": {
            },
            "index": 37,
            "label": "Onset",
            "originalEndDatetime": "2020-12-28T14:41:55.208420+03:00",
            "originalStartDatetime": "2020-12-28T14:41:55.208420+03:00",
            "port": "KeyStroke",
            "startDatetime": "2020-12-28T14:41:55.204673+03:00",
            "type": "instance",
            "uuid": "041d52d2-b36e-410d-970c-25c2c674c681",
            "value": 1
        },
        {
            "endDatetime": "2020-12-28T14:42:03.212808+03:00",
            "extras": {
            },
            "index": 38,
            "label": "Onset",
            "originalEndDatetime": "2020-12-28T14:42:03.213840+03:00",
            "originalStartDatetime": "2020-12-28T14:42:03.213840+03:00",
            "port": "KeyStroke",
            "startDatetime": "2020-12-28T14:42:03.212808+03:00",
            "type": "instance",
            "uuid": "35898c07-39e5-4654-ab4c-ccc7079ddae8",
            "value": 1
        },
        {
            "endDatetime": "2020-12-28T14:42:11.214428+03:00",
            "extras": {
            },
            "index": 39,
            "label": "Onset",
            "originalEndDatetime": "2020-12-28T14:42:11.213469+03:00",
            "originalStartDatetime": "2020-12-28T14:42:11.213469+03:00",
            "port": "KeyStroke",
            "startDatetime": "2020-12-28T14:42:11.214428+03:00",
            "type": "instance",
            "uuid": "57f77363-c732-482b-af99-b6f66fee7437",
            "value": 1
        },
        {
            "endDatetime": "2020-12-28T14:42:19.207036+03:00",
            "extras": {
            },
            "index": 40,
            "label": "Onset",
            "originalEndDatetime": "2020-12-28T14:42:19.209057+03:00",
            "originalStartDatetime": "2020-12-28T14:42:19.209057+03:00",
            "port": "KeyStroke",
            "startDatetime": "2020-12-28T14:42:19.207036+03:00",
            "type": "instance",
            "uuid": "06194971-9369-4640-bdc2-41da16148e08",
            "value": 1
        },
        {
            "endDatetime": "2020-12-28T14:42:27.214867+03:00",
            "extras": {
            },
            "index": 41,
            "label": "Onset",
            "originalEndDatetime": "2020-12-28T14:42:27.211657+03:00",
            "originalStartDatetime": "2020-12-28T14:42:27.211657+03:00",
            "port": "KeyStroke",
            "startDatetime": "2020-12-28T14:42:27.214867+03:00",
            "type": "instance",
            "uuid": "33c953cc-feff-4d51-80c9-2567203d1663",
            "value": 1
        },
        {
            "endDatetime": "2020-12-28T14:42:35.223813+03:00",
            "extras": {
            },
            "index": 42,
            "label": "Onset",
            "originalEndDatetime": "2020-12-28T14:42:35.225688+03:00",
            "originalStartDatetime": "2020-12-28T14:42:35.225688+03:00",
            "port": "KeyStroke",
            "startDatetime": "2020-12-28T14:42:35.223813+03:00",
            "type": "instance",
            "uuid": "db97ccb1-8cb8-493b-ae27-e116bc6edbeb",
            "value": 1
        },
        {
            "endDatetime": "2020-12-28T14:42:43.231777+03:00",
            "extras": {
            },
            "index": 43,
            "label": "Onset",
            "originalEndDatetime": "2020-12-28T14:42:43.230464+03:00",
            "originalStartDatetime": "2020-12-28T14:42:43.230464+03:00",
            "port": "KeyStroke",
            "startDatetime": "2020-12-28T14:42:43.231777+03:00",
            "type": "instance",
            "uuid": "e159ca79-8127-4445-9a6a-e925c7fb6206",
            "value": 1
        },
        {
            "endDatetime": "2020-12-28T14:42:51.233512+03:00",
            "extras": {
            },
            "index": 44,
            "label": "Onset",
            "originalEndDatetime": "2020-12-28T14:42:51.235335+03:00",
            "originalStartDatetime": "2020-12-28T14:42:51.235335+03:00",
            "port": "KeyStroke",
            "startDatetime": "2020-12-28T14:42:51.233512+03:00",
            "type": "instance",
            "uuid": "d376449e-8dd4-48d1-a48a-3ab8bd0b7d8b",
            "value": 1
        },
        {
            "endDatetime": "2020-12-28T14:42:59.217085+03:00",
            "extras": {
            },
            "index": 45,
            "label": "Onset",
            "originalEndDatetime": "2020-12-28T14:42:59.216408+03:00",
            "originalStartDatetime": "2020-12-28T14:42:59.216408+03:00",
            "port": "KeyStroke",
            "startDatetime": "2020-12-28T14:42:59.217085+03:00",
            "type": "instance",
            "uuid": "e5fba294-5f2a-4a3b-83d8-529b191456fa",
            "value": 1
        },
        {
            "endDatetime": "2020-12-28T14:43:07.218350+03:00",
            "extras": {
            },
            "index": 46,
            "label": "Onset",
            "originalEndDatetime": "2020-12-28T14:43:07.214780+03:00",
            "originalStartDatetime": "2020-12-28T14:43:07.214780+03:00",
            "port": "KeyStroke",
            "startDatetime": "2020-12-28T14:43:07.218350+03:00",
            "type": "instance",
            "uuid": "e73c667a-9bb8-48a5-b7dc-76d0c6d2ab79",
            "value": 1
        },
        {
            "endDatetime": "2020-12-28T14:43:15.203788+03:00",
            "extras": {
            },
            "index": 47,
            "label": "Onset",
            "originalEndDatetime": "2020-12-28T14:43:15.207077+03:00",
            "originalStartDatetime": "2020-12-28T14:43:15.207077+03:00",
            "port": "KeyStroke",
            "startDatetime": "2020-12-28T14:43:15.203788+03:00",
            "type": "instance",
            "uuid": "ee078953-4067-45da-9ea6-6ad33d160f21",
            "value": 1
        },
        {
            "endDatetime": "2020-12-28T14:43:23.196433+03:00",
            "extras": {
            },
            "index": 48,
            "label": "Onset",
            "originalEndDatetime": "2020-12-28T14:43:23.192881+03:00",
            "originalStartDatetime": "2020-12-28T14:43:23.192881+03:00",
            "port": "KeyStroke",
            "startDatetime": "2020-12-28T14:43:23.196433+03:00",
            "type": "instance",
            "uuid": "93b92ef2-dc89-4efd-9a87-8f186e35de28",
            "value": 1
        },
        {
            "endDatetime": "2020-12-28T14:43:31.197216+03:00",
            "extras": {
            },
            "index": 49,
            "label": "Onset",
            "originalEndDatetime": "2020-12-28T14:43:31.197086+03:00",
            "originalStartDatetime": "2020-12-28T14:43:31.197086+03:00",
            "port": "KeyStroke",
            "startDatetime": "2020-12-28T14:43:31.197216+03:00",
            "type": "instance",
            "uuid": "475b4b3d-99c7-4c44-8637-7f632a538717",
            "value": 1
        },
        {
            "endDatetime": "2020-12-28T14:43:39.190010+03:00",
            "extras": {
            },
            "index": 50,
            "label": "Onset",
            "originalEndDatetime": "2020-12-28T14:43:39.190711+03:00",
            "originalStartDatetime": "2020-12-28T14:43:39.190711+03:00",
            "port": "KeyStroke",
            "startDatetime": "2020-12-28T14:43:39.190010+03:00",
            "type": "instance",
            "uuid": "90594463-5b5b-40cb-8262-5714b6745b07",
            "value": 1
        },
        {
            "endDatetime": "2020-12-28T14:43:47.198622+03:00",
            "extras": {
            },
            "index": 51,
            "label": "Onset",
            "originalEndDatetime": "2020-12-28T14:43:47.201882+03:00",
            "originalStartDatetime": "2020-12-28T14:43:47.201882+03:00",
            "port": "KeyStroke",
            "startDatetime": "2020-12-28T14:43:47.198622+03:00",
            "type": "instance",
            "uuid": "a8f5c620-8c6b-4168-ad52-0dab06adb9e1",
            "value": 1
        }
    ],
    "cqMode": 0,
    "exportApp": "com.emotiv.emotivpro",
    "exportTime": "2020-12-28T15:32:17.675+03:00",
    "mappings": {
        "CMS": "TP9",
        "DRL": "TP10",
        "LA": "F1",
        "LB": "FCz",
        "LC": "FC1",
        "LD": "FC3",
        "LE": "FC5",
        "LF": "Cz",
        "LG": "C1",
        "LH": "C3",
        "LJ": "C5",
        "LK": "CPz",
        "LL": "CP1",
        "LM": "CP3",
        "LN": "CP5",
        "LO": "P1",
        "LP": "P3",
        "LQ": "P5",
        "RA": "Afz",
        "RB": "Fz",
        "RC": "F2",
        "RD": "FC2",
        "RE": "FC4",
        "RF": "FC6",
        "RG": "C2",
        "RH": "C4",
        "RJ": "C6",
        "RK": "CP2",
        "RL": "CP4",
        "RM": "CP6",
        "RN": "Pz",
        "RO": "P2",
        "RP": "P4",
        "RQ": "P6"
    },
    "recordId": "649c95c9-3ef5-4e49-be05-04906d8e19bd",
    "user": "umar_cse"
}
